function/__init__.py
function/test_t.py
create_p_test-1.1.dist-info/METADATA
create_p_test-1.1.dist-info/WHEEL
create_p_test-1.1.dist-info/top_level.txt
create_p_test-1.1.dist-info/RECORD
